emojy/__init__.py
emojy/__main__.py
emojy/emoji_table.py
emojy-0.2.0.dist-info/LICENSE
emojy-0.2.0.dist-info/METADATA
emojy-0.2.0.dist-info/WHEEL
emojy-0.2.0.dist-info/entry_points.txt
emojy-0.2.0.dist-info/top_level.txt
emojy-0.2.0.dist-info/RECORD
